{
  "last_updated": "02/07/2026 16:53",
  "count": 12,
  "ofertas": [
    {
      "titulo": "Técnico/a oficina de turismo en herrera del duque",
      "id": "3650",
      "enlace": "https://sexpeemplea.juntaex.es/OfertasOrientacion/?id_menu=3650",
      "fuente": "SEXPE",
      "ubicacion": "Mérida (Automático)"
    },
    {
      "titulo": "Conserje con discapacidad/ayuntamiento de torrejón el rubio",
      "id": "3868",
      "enlace": "https://sexpeemplea.juntaex.es/OfertasOrientacion/?id_menu=3868",
      "fuente": "SEXPE",
      "ubicacion": "Mérida (Automático)"
    },
    {
      "titulo": "Auxiliar de enfermería santa marta de magasca 4",
      "id": "3918",
      "enlace": "https://sexpeemplea.juntaex.es/OfertasOrientacion/?id_menu=3918",
      "fuente": "SEXPE",
      "ubicacion": "Mérida (Automático)"
    },
    {
      "titulo": "Asesor/a jurídico/a. mancomunidad integral de servicios la serena vegas altas",
      "id": "3930",
      "enlace": "https://sexpeemplea.juntaex.es/OfertasOrientacion/?id_menu=3930",
      "fuente": "SEXPE",
      "ubicacion": "Mérida (Automático)"
    },
    {
      "titulo": "OF. 2ª MANTENIMIENTO PARA EL CAM JARDÍN DEL SAUCE POR LA VICEPRESIDENCIA Y CONSEJ DE DESREGULACIÓN SERV. SOC. Y FAMILIA EN CÁCERES",
      "id": "3931",
      "enlace": "https://sexpeemplea.juntaex.es/OfertasOrientacion/?id_menu=3931",
      "fuente": "SEXPE",
      "ubicacion": "Mérida (Automático)"
    },
    {
      "titulo": "Director/a de ocio y tiempo libre. ayto robledollano",
      "id": "3932",
      "enlace": "https://sexpeemplea.juntaex.es/OfertasOrientacion/?id_menu=3932",
      "fuente": "SEXPE",
      "ubicacion": "Mérida (Automático)"
    },
    {
      "titulo": "Auxiliar de enfermería (varios puestos) por el sepad en varias localidades de las prov. de cáceres y badajoz.",
      "id": "3933",
      "enlace": "https://sexpeemplea.juntaex.es/OfertasOrientacion/?id_menu=3933",
      "fuente": "SEXPE",
      "ubicacion": "Mérida (Automático)"
    },
    {
      "titulo": "Director de ocio y tiempo libre (concilia-extremadura) berrocalejo(caceres)",
      "id": "3934",
      "enlace": "https://sexpeemplea.juntaex.es/OfertasOrientacion/?id_menu=3934",
      "fuente": "SEXPE",
      "ubicacion": "Mérida (Automático)"
    },
    {
      "titulo": "Técnico superior en prevención de riesgos laborales",
      "id": "3935",
      "enlace": "https://sexpeemplea.juntaex.es/OfertasOrientacion/?id_menu=3935",
      "fuente": "SEXPE",
      "ubicacion": "Mérida (Automático)"
    },
    {
      "titulo": "4 OFCIALES 2ª MECÁNICA POR LA VICEP. Y CONSEJ. DE PRESIDENCIA, COORDINACIÓN DE LA ACCIÓN DE GOBIERNO, INTERIOR Y EMERGENCIAS",
      "id": "3936",
      "enlace": "https://sexpeemplea.juntaex.es/OfertasOrientacion/?id_menu=3936",
      "fuente": "SEXPE",
      "ubicacion": "Mérida (Automático)"
    },
    {
      "titulo": "Cocinero/a para el sepad en gata y herrera del duque",
      "id": "3937",
      "enlace": "https://sexpeemplea.juntaex.es/OfertasOrientacion/?id_menu=3937",
      "fuente": "SEXPE",
      "ubicacion": "Mérida (Automático)"
    },
    {
      "titulo": "Director/a ocio y tiempo libre/ayuntamiento de torrejón el rubio",
      "id": "3938",
      "enlace": "https://sexpeemplea.juntaex.es/OfertasOrientacion/?id_menu=3938",
      "fuente": "SEXPE",
      "ubicacion": "Mérida (Automático)"
    }
  ]
}