{
  "last_updated": "14/04/2026 19:44",
  "count": 16,
  "ofertas": [
    {
      "id": "112026006593",
      "titulo": "Ingeniero técnico industrial para el inst. del corcho, la madera y el carbón vegetal (icmc), perteneciente al cicytex en mérida.",
      "fecha": "14/04/2026",
      "ubicacion": "Merida\n\t\t\t\t\t\n\t\t\t\t\t\t(Badajoz)",
      "enlace": "https://www.sistemanacionalempleo.es/OfertaDifusionWEB/detalleOferta.do?modo=inicio&id=112026006593&ret=B&idFlujo=rWt9jfj_h4BjxMOZ_N3Kdze3139",
      "fuente": "SNE"
    },
    {
      "id": "112026003639",
      "titulo": "Oficial de carpinteria ó montador de carpintería",
      "fecha": "14/04/2026",
      "ubicacion": "Merida\n\t\t\t\t\t\n\t\t\t\t\t\t(Badajoz)",
      "enlace": "https://www.sistemanacionalempleo.es/OfertaDifusionWEB/detalleOferta.do?modo=inicio&id=112026003639&ret=B&idFlujo=rWt9jfj_h4BjxMOZ_N3Kdze3139",
      "fuente": "SNE"
    },
    {
      "id": "112026006589",
      "titulo": "Ayudante camarero/a",
      "fecha": "13/04/2026",
      "ubicacion": "Merida\n\t\t\t\t\t\n\t\t\t\t\t\t(Badajoz)",
      "enlace": "https://www.sistemanacionalempleo.es/OfertaDifusionWEB/detalleOferta.do?modo=inicio&id=112026006589&ret=B&idFlujo=rWt9jfj_h4BjxMOZ_N3Kdze3139",
      "fuente": "SNE"
    },
    {
      "id": "112026004722",
      "titulo": "Administrativo contable",
      "fecha": "13/04/2026",
      "ubicacion": "Merida\n\t\t\t\t\t\n\t\t\t\t\t\t(Badajoz)",
      "enlace": "https://www.sistemanacionalempleo.es/OfertaDifusionWEB/detalleOferta.do?modo=inicio&id=112026004722&ret=B&idFlujo=rWt9jfj_h4BjxMOZ_N3Kdze3139",
      "fuente": "SNE"
    },
    {
      "id": "112026006449",
      "titulo": "Cocinero",
      "fecha": "10/04/2026",
      "ubicacion": "Merida\n\t\t\t\t\t\n\t\t\t\t\t\t(Badajoz)",
      "enlace": "https://www.sistemanacionalempleo.es/OfertaDifusionWEB/detalleOferta.do?modo=inicio&id=112026006449&ret=B&idFlujo=rWt9jfj_h4BjxMOZ_N3Kdze3139",
      "fuente": "SNE"
    },
    {
      "id": "112026000320",
      "titulo": "Jefe de cocina",
      "fecha": "10/04/2026",
      "ubicacion": "Merida\n\t\t\t\t\t\n\t\t\t\t\t\t(Badajoz)",
      "enlace": "https://www.sistemanacionalempleo.es/OfertaDifusionWEB/detalleOferta.do?modo=inicio&id=112026000320&ret=B&idFlujo=rWt9jfj_h4BjxMOZ_N3Kdze3139",
      "fuente": "SNE"
    },
    {
      "id": "112026006208",
      "titulo": "Auxiliar ayuda a domicilio, instituciones sociales o de enfermeria",
      "fecha": "08/04/2026",
      "ubicacion": "Merida\n\t\t\t\t\t\n\t\t\t\t\t\t(Badajoz)",
      "enlace": "https://www.sistemanacionalempleo.es/OfertaDifusionWEB/detalleOferta.do?modo=inicio&id=112026006208&ret=B&idFlujo=rWt9jfj_h4BjxMOZ_N3Kdze3139",
      "fuente": "SNE"
    },
    {
      "id": "112026003023",
      "titulo": "Chapista",
      "fecha": "07/04/2026",
      "ubicacion": "Merida\n\t\t\t\t\t\n\t\t\t\t\t\t(Badajoz)",
      "enlace": "https://www.sistemanacionalempleo.es/OfertaDifusionWEB/detalleOferta.do?modo=inicio&id=112026003023&ret=B&idFlujo=rWt9jfj_h4BjxMOZ_N3Kdze3139",
      "fuente": "SNE"
    },
    {
      "id": "112026003012",
      "titulo": "Mecánico/a",
      "fecha": "07/04/2026",
      "ubicacion": "Merida\n\t\t\t\t\t\n\t\t\t\t\t\t(Badajoz)",
      "enlace": "https://www.sistemanacionalempleo.es/OfertaDifusionWEB/detalleOferta.do?modo=inicio&id=112026003012&ret=B&idFlujo=rWt9jfj_h4BjxMOZ_N3Kdze3139",
      "fuente": "SNE"
    },
    {
      "id": "112026003010",
      "titulo": "Pintor/a de vehículos",
      "fecha": "07/04/2026",
      "ubicacion": "Merida\n\t\t\t\t\t\n\t\t\t\t\t\t(Badajoz)",
      "enlace": "https://www.sistemanacionalempleo.es/OfertaDifusionWEB/detalleOferta.do?modo=inicio&id=112026003010&ret=B&idFlujo=rWt9jfj_h4BjxMOZ_N3Kdze3139",
      "fuente": "SNE"
    },
    {
      "id": "112026006059",
      "titulo": "Ingeniero/a de diseño de producto",
      "fecha": "06/04/2026",
      "ubicacion": "Merida\n\t\t\t\t\t\n\t\t\t\t\t\t(Badajoz)",
      "enlace": "https://www.sistemanacionalempleo.es/OfertaDifusionWEB/detalleOferta.do?modo=inicio&id=112026006059&ret=B&idFlujo=rWt9jfj_h4BjxMOZ_N3Kdze3139",
      "fuente": "SNE"
    },
    {
      "id": "112026006055",
      "titulo": "Técnico/a instalador/a y mantenimiento",
      "fecha": "06/04/2026",
      "ubicacion": "Merida\n\t\t\t\t\t\n\t\t\t\t\t\t(Badajoz)",
      "enlace": "https://www.sistemanacionalempleo.es/OfertaDifusionWEB/detalleOferta.do?modo=inicio&id=112026006055&ret=B&idFlujo=rWt9jfj_h4BjxMOZ_N3Kdze3139",
      "fuente": "SNE"
    },
    {
      "id": "112026006010",
      "titulo": "Recepcionista de apartamentos",
      "fecha": "06/04/2026",
      "ubicacion": "Merida\n\t\t\t\t\t\n\t\t\t\t\t\t(Badajoz)",
      "enlace": "https://www.sistemanacionalempleo.es/OfertaDifusionWEB/detalleOferta.do?modo=inicio&id=112026006010&ret=B&idFlujo=rWt9jfj_h4BjxMOZ_N3Kdze3139",
      "fuente": "SNE"
    },
    {
      "id": "112026005999",
      "titulo": "Contable",
      "fecha": "06/04/2026",
      "ubicacion": "Merida\n\t\t\t\t\t\n\t\t\t\t\t\t(Badajoz)",
      "enlace": "https://www.sistemanacionalempleo.es/OfertaDifusionWEB/detalleOferta.do?modo=inicio&id=112026005999&ret=B&idFlujo=rWt9jfj_h4BjxMOZ_N3Kdze3139",
      "fuente": "SNE"
    },
    {
      "id": "112026005099",
      "titulo": "7 puestos de ingeniero informático",
      "fecha": "19/03/2026",
      "ubicacion": "Merida\n\t\t\t\t\t\n\t\t\t\t\t\t(Badajoz)",
      "enlace": "https://www.sistemanacionalempleo.es/OfertaDifusionWEB/detalleOferta.do?modo=inicio&id=112026005099&ret=B&idFlujo=rWt9jfj_h4BjxMOZ_N3Kdze3139",
      "fuente": "SNE"
    },
    {
      "id": "112026002248",
      "titulo": "Conductor/a camión con discapacidad",
      "fecha": "09/02/2026",
      "ubicacion": "Merida\n\t\t\t\t\t\n\t\t\t\t\t\t(Badajoz)",
      "enlace": "https://www.sistemanacionalempleo.es/OfertaDifusionWEB/detalleOferta.do?modo=inicio&id=112026002248&ret=B&idFlujo=rWt9jfj_h4BjxMOZ_N3Kdze3139",
      "fuente": "SNE"
    }
  ]
}